credcheck/__init__.py
credcheck/cli.py
credcheck/cred.py
credcheck-0.0.3.dist-info/METADATA
credcheck-0.0.3.dist-info/WHEEL
credcheck-0.0.3.dist-info/top_level.txt
credcheck-0.0.3.dist-info/RECORD
