Metadata-Version: 2.1
Name: credcheck
Version: 0.0.3
Summary: A tool to determine Crossref credential permissions.
Home-page: https://gitlab.com/crossref/labs/credCheck
Author: Martin Paul Eve
Author-email: meve@crossref.org
Maintainer-email: Martin Paul Eve <meve@crossref.org>
Project-URL: homepage, https://labs.crossref.org
Project-URL: documentation, https://labs.crossref.org
Project-URL: repository, https://gitlab.com/crossref/labs/credCheck
Keywords: digital-preservation,crossref
Classifier: Development Status :: 4 - Beta
Classifier: Programming Language :: Python
Requires-Python: >=3.8
Requires-Dist: requests
Requires-Dist: rich
Requires-Dist: typer
